[
    {
      "grade": 1,
      "subject": "English",
      "type":"Games",
      "Games":[

        {
          "name": "Flappy Plane",
          "image": "flappy.png",
          "alt":"image3",
          "link": "assets\\games\\Grade2\\English\\Flappy Plane\\flaps.exe"
        },
        {
          "name": "Vowels",
          "image": "vowels.png",
          "alt":"image3",
          "link": "assets\\games\\Grade2\\English\\Vowels\\Vowels.exe"
        },
        {
          "name": "Animal Quiz",
          "image": "Animal-Quiz.png",
          "alt":"image3",
          "link": "assets\\games\\Grade2\\English\\Animal Quiz\\Animal-Quiz.exe"
        },
        {
          "name": "Articles",
          "image": "Articles.png",
          "alt":"image3",
          "link": "assets\\games\\Grade2\\English\\Articles\\Articles.exe"
        }
      ]
}
]

