[
  {
    "grade": 6,
    "subject": "Computer",
    "type": "Interactive Content",
    "Interactive": [
      {
        "Heading": "Computer Memory",
        "interactive_items": [
          {
            "name": "Introduction and units of memory",
            "link": "assets\\H5P\\Grade 6\\Computer\\Computer Memory\\introduction-and-units-of-memory\\introduction-and-units-of-memory.html"
          },
          {
            "name": "Primary memory",
            "link": "assets\\H5P\\Grade 6\\Computer\\Computer Memory\\primary-memory\\primary-memory.html"
          },
          {
            "name": "Secondary memory",
            "link": "assets\\H5P\\Grade 6\\Computer\\Computer Memory\\secondary-memory\\secondary-memory.html"
          }
        ]
      },
      {
        "Heading": "Computer software",
        "interactive_items": [
          {
            "name": "Application software",
            "link": "assets\\H5P\\Grade 6\\Computer\\Computer software\\application-software\\application-software.html"
          },
          {
            "name": "System software",
            "link": "assets\\H5P\\Grade 6\\Computer\\Computer software\\system-software\\system-software.html"
          }
        ]
      },
      {
        "Heading": "Computer system",
        "interactive_items": [
          {
            "name": "Computer software and hardware",
            "link": "assets\\H5P\\Grade 6\\Computer\\Computer system\\computer-software-and-hardware\\computer-software-and-hardware.html"
          },
          {
            "name": "Input unit",
            "link": "assets\\H5P\\Grade 6\\Computer\\Computer system\\computer-system\\computer-system.html"
          },
          {
            "name": "Output unit",
            "link": "assets\\H5P\\Grade 6\\Computer\\Computer system\\output-unit\\output-unit.html"
          }
        ]
      },
      {
        "Heading": "Computer virus",
        "interactive_items": [
          {
            "name": "Antivirus and preventive measures",
            "link": "assets\\H5P\\Grade 6\\Computer\\Computer virus\\antivirus-and-preventive-measures\\antivirus-and-preventive-measures.html"
          },
          {
            "name": "Introduction and types of computer virus",
            "link": "assets\\H5P\\Grade 6\\Computer\\Computer virus\\introduction-and-types-of-computer-virus\\introduction-and-types-of-computer-virus.html"
          },
          {
            "name": "Transmission and effects of computer virus",
            "link": "assets\\H5P\\Grade 6\\Computer\\Computer virus\\transmission-and-effects-of-computer-virus\\transmission-and-effects-of-computer-virus.html"
          }
        ]
      },
      {
        "Heading": "ICT and computer ethics",
        "interactive_items": [
          {
            "name": "Computer ethics",
            "link": "assets\\H5P\\Grade 6\\Computer\\ICT and computer ethics\\computer-ethics\\computer-ethics.html"
          },
          {
            "name": "Introduction of ICT",
            "link": "assets\\H5P\\Grade 6\\Computer\\ICT and computer ethics\\introduction-of-ict\\introduction-of-ict.html"
          },
          {
            "name": "Usage of ICT in daily life",
            "link": "assets\\H5P\\Grade 6\\Computer\\ICT and computer ethics\\usage-of-ict-in-daily-life\\usage-of-ict-in-daily-life.html"
          }
        ]
      },
      {
        "Heading": "Introduction to computer and its generations",
        "interactive_items": [
          {
            "name": "Introduction to computer",
            "link": "assets\\H5P\\Grade 6\\Computer\\Introduction to computer and its generations\\introduction-to-computer\\introduction-to-computer.html"
          },
          {
            "name": "Characteristics of a computer",
            "link": "assets\\H5P\\Grade 6\\Computer\\Introduction to computer and its generations\\characteristics-of-a-computer\\characteristics-of-a-computer.html"
          },
          {
            "name": "First generation computers",
            "link": "assets\\H5P\\Grade 6\\Computer\\Introduction to computer and its generations\\first-generation-computers\\first-generation-computers.html"
          },
          {
            "name": "Second generation computers",
            "link": "assets\\H5P\\Grade 6\\Computer\\Introduction to computer and its generations\\second-generation-computers\\second-generation-computers.html"
          },
          {
            "name": "Third generation computers",
            "link": "assets\\H5P\\Grade 6\\Computer\\Introduction to computer and its generations\\third-generation-computers\\third-generation-computers.html"
          },
          {
            "name": "Fourth generation computers",
            "link": "assets\\H5P\\Grade 6\\Computer\\Introduction to computer and its generations\\fourth-generation-computers\\fourth-generation-computers.html"
          },
          {
            "name": "Fifth generation computers",
            "link": "assets\\H5P\\Grade 6\\Computer\\Introduction to computer and its generations\\fifth-generation-computers\\fifth-generation-computers.html"
          },
          {
            "name": "Limitations and application of a computer",
            "link": "assets\\H5P\\Grade 6\\Computer\\Introduction to computer and its generations\\limitations-and-application-of-a-computer\\limitations-and-application-of-a-computer.html"
          }
        ]
      },
      {
        "Heading": "Introduction to Internet and E-mail",
        "interactive_items": [
          {
            "name": "Email",
            "link": "assets\\H5P\\Grade 6\\Computer\\Introduction to internet and e-mail\\email\\email.html"
          },
          {
            "name": "Internet",
            "link": "assets\\H5P\\Grade 6\\Computer\\Introduction to Internet and E-mail\\internet\\internet.html"
          },
          {
            "name": "Internet based services and terms used in internet",
            "link": "assets\\H5P\\Grade 6\\Computer\\Introduction to Internet and E-mail\\internet-based-services-and-terms-used-in-internet\\internet-based-services-and-terms-used-in-internet.html"
          }
        ]
      },
      {
        "Heading": "Introduction to presentation software: Microsoft Powerpoint",
        "interactive_items": [
          {
            "name": "Starting MS Powerpoint",
            "link": "assets\\H5P\\Grade 6\\Computer\\Introduction to presentation software Microsoft Powerpoint\\starting-ms-powerpoint\\starting-ms-powerpoint.html"
          },
          {
            "name": "Inserting objects in Powerpoint",
            "link": "assets\\H5P\\Grade 6\\Computer\\Introduction to presentation software Microsoft Powerpoint\\inserting-objects-in-powerpoint\\inserting-objects-in-powerpoint.html"
          },
          {
            "name": "More information on MS Powerpoint",
            "link": "assets\\H5P\\Grade 6\\Computer\\Introduction to presentation software Microsoft Powerpoint\\more-information-on-ms-powerpoint\\more-information-on-ms-powerpoint.html"
          }
        ]
      },
      {
        "Heading": "Introduction to QBASIC programming",
        "interactive_items": [
          {
            "name": "QBASIC statements",
            "link": "assets\\H5P\\Grade 6\\Computer\\Introduction to QBASIC programming\\qbasic-statements\\qbasic-statements.html"
          },
          {
            "name": "Graphics in QBASIC",
            "link": "assets\\H5P\\Grade 6\\Computer\\Introduction to QBASIC programming\\graphics-in-qbasic\\graphics-in-qbasic.html"
          },
          {
            "name": "QBASIC",
            "link": "assets\\H5P\\Grade 6\\Computer\\Introduction to QBASIC programming\\qbasic\\qbasic.html"
          },
          {
            "name": "Starting QBASIC",
            "link": "assets\\H5P\\Grade 6\\Computer\\Introduction to QBASIC programming\\starting-qbasic\\starting-qbasic.html"
          },
          {
            "name": "Constants and variables",
            "link": "assets\\H5P\\Grade 6\\Computer\\Introduction to QBASIC programming\\constants-and-variables\\constants-and-variables.html"
          },
          {
            "name": "Operators and expressions",
            "link": "assets\\H5P\\Grade 6\\Computer\\Introduction to QBASIC programming\\operators-and-expressions\\operators-and-expressions.html"
          }
        ]
      },
      {
        "Heading": "Introduction to spreadsheet: microsoft excel",
        "interactive_items": [
          {
            "name": "The ms-excel screen",
            "link": "assets\\H5P\\Grade 6\\Computer\\Introduction to spreadsheet microsoft excel\\the-ms-excel-screen\\the-ms-excel-screen.html"
          },
          {
            "name": "Formulas in worksheet",
            "link": "assets\\H5P\\Grade 6\\Computer\\Introduction to spreadsheet microsoft excel\\Formulas in worksheet\\Formulas in worksheet.html"
          },
          {
            "name": "Working with chart",
            "link": "assets\\H5P\\Grade 6\\Computer\\Introduction to spreadsheet microsoft excel\\working-with-chart\\working-with-chart.html"
          }
        ]
      },
      {
        "Heading": "Introduction to word processing: microsoft word",
        "interactive_items": [
          {
            "name": "Date, time and inserting special symbols",
            "link": "assets\\H5P\\Grade 6\\Computer\\Introduction to word processing microsoft word\\Date, time and inserting special symbols\\Date, time and inserting special symbols.html"
          },
          {
            "name": "Different functions of word",
            "link": "assets\\H5P\\Grade 6\\Computer\\Introduction to word processing microsoft word\\different-functions-of-word\\different-functions-of-word.html"
          },
          {
            "name": "Printing",
            "link": "assets\\H5P\\Grade 6\\Computer\\Introduction to word processing microsoft word\\printing\\printing.html"
          }
        ]
      },
      {
        "Heading": "Operating system",
        "interactive_items": [
          {
            "name": "Introduction and functions of operating system",
            "link": "assets\\H5P\\Grade 6\\Computer\\Operating system\\introduction-and-functions-of-operating-system\\introduction-and-functions-of-operating-system.html"
          },
          {
            "name": "Windows 7",
            "link": "assets\\H5P\\Grade 6\\Computer\\Operating system\\windows-7\\windows-7.html"
          },
          {
            "name": "The user interface",
            "link": "assets\\H5P\\Grade 6\\Computer\\Operating system\\the-user-interface\\the-user-interface.html"
          },
          {
            "name": "Booting",
            "link": "assets\\H5P\\Grade 6\\Computer\\Operating system\\booting\\booting.html"
          },
          {
            "name": "Terms used in MS-DOS",
            "link": "assets\\H5P\\Grade 6\\Computer\\Operating system\\terms-used-in-ms-dos\\terms-used-in-ms-dos.html"
          },
          {
            "name": "MS-DOS Commands",
            "link": "assets\\H5P\\Grade 6\\Computer\\Operating system\\ms-dos-commands\\ms-dos-commands.html"
          }
        ]
    }

    ]
  }
]